NewtonMathSolver/__init__.py
NewtonMathSolver/solve.py
NewtonMathSolver-0.1.0.dist-info/METADATA
NewtonMathSolver-0.1.0.dist-info/WHEEL
NewtonMathSolver-0.1.0.dist-info/top_level.txt
NewtonMathSolver-0.1.0.dist-info/RECORD
