Metadata-Version: 2.1
Name: NewtonMathSolver
Version: 0.1.0
Summary: Use newton method to iterate infinitely to find an approximate solution to any equation.
Home-page: https://github.com/MoYeRanqianzhi/NewtonMathSolver
Author: MoYeRanQianZhi
Author-email: moyeranqianzhi@gmail.com
License: MIT License
Classifier: Development Status :: 3 - Alpha
Classifier: Intended Audience :: Developers
Classifier: License :: OSI Approved :: MIT License
Classifier: Programming Language :: Python
Classifier: Programming Language :: Python :: 3
Classifier: Programming Language :: Python :: 3.6
Classifier: Programming Language :: Python :: 3.7
Classifier: Programming Language :: Python :: 3.8
Classifier: Programming Language :: Python :: 3.9
Classifier: Programming Language :: Python :: 3.10
Classifier: Programming Language :: Python :: 3.11
Classifier: Programming Language :: Python :: 3.12
Requires: sympy
Requires-Python: >=3.6.0
